gridfm_datakit/__init__.py
gridfm_datakit/cli.py
gridfm_datakit/generate.py
gridfm_datakit/interactive.py
gridfm_datakit/network.py
gridfm_datakit/save.py
gridfm_datakit/validation.py
gridfm_datakit/grids/__init__.py
gridfm_datakit/load_profiles/__init__.py
gridfm_datakit/load_profiles/default.csv
gridfm_datakit/load_profiles/ercot_load_act_hr_2024_coast.csv
gridfm_datakit/load_profiles/ercot_load_act_hr_2024_east.csv
gridfm_datakit/load_profiles/ercot_load_act_hr_2024_far_west.csv
gridfm_datakit/load_profiles/ercot_load_act_hr_2024_north.csv
gridfm_datakit/load_profiles/ercot_load_act_hr_2024_north_central.csv
gridfm_datakit/load_profiles/ercot_load_act_hr_2024_south_central.csv
gridfm_datakit/load_profiles/ercot_load_act_hr_2024_southern.csv
gridfm_datakit/load_profiles/ercot_load_act_hr_2024_total.csv
gridfm_datakit/load_profiles/ercot_load_act_hr_2024_west.csv
gridfm_datakit/perturbations/__init__.py
gridfm_datakit/perturbations/admittance_perturbation.py
gridfm_datakit/perturbations/generator_perturbation.py
gridfm_datakit/perturbations/load_perturbation.py
gridfm_datakit/perturbations/topology_perturbation.py
gridfm_datakit/process/__init__.py
gridfm_datakit/process/process_network.py
gridfm_datakit/process/solvers.py
gridfm_datakit/utils/__init__.py
gridfm_datakit/utils/column_names.py
gridfm_datakit/utils/idx_brch.py
gridfm_datakit/utils/idx_bus.py
gridfm_datakit/utils/idx_cost.py
gridfm_datakit/utils/idx_gen.py
gridfm_datakit/utils/param_handler.py
gridfm_datakit/utils/power_balance.py
gridfm_datakit/utils/stats.py
gridfm_datakit/utils/utils.py
gridfm_datakit-1.0.1.dist-info/licenses/LICENSE
gridfm_datakit-1.0.1.dist-info/METADATA
gridfm_datakit-1.0.1.dist-info/WHEEL
gridfm_datakit-1.0.1.dist-info/entry_points.txt
gridfm_datakit-1.0.1.dist-info/top_level.txt
gridfm_datakit-1.0.1.dist-info/RECORD
