Metadata-Version: 2.4
Name: gridfm-datakit
Version: 1.0.1
Summary: Data Generation Kit
Author-email: Alban Puech <alban.puech2@ibm.com>, Matteo Mazzonelli <matteo.mazzonelli1@ibm.com>, Tamara Govindasamy <tamara.govindasamy@ibm.com>, Mangaliso Mngomezulu <mngomezulum@ibm.com>, Etienne Vos <etienne.vos@ibm.com>, Jonas Weiss <jwe@zurich.ibm.com>
Maintainer-email: Alban Puech <apuech@seas.harvard.edu>
License-Expression: Apache-2.0
Classifier: Development Status :: 2 - Pre-Alpha
Classifier: Programming Language :: Python :: 3.10
Classifier: Programming Language :: Python :: 3.11
Classifier: Programming Language :: Python :: 3.12
Classifier: Topic :: Scientific/Engineering
Requires-Python: <3.13,>=3.10
License-File: LICENSE
Requires-Dist: ipykernel
Requires-Dist: matplotlib
Requires-Dist: matpowercaseframes
Requires-Dist: nbformat
Requires-Dist: numba
Requires-Dist: numpy
Requires-Dist: pandas
Requires-Dist: pathlib
Requires-Dist: plotly
Requires-Dist: pyaml
Requires-Dist: requests
Requires-Dist: urllib3<2.0.0
Requires-Dist: ipywidgets
Requires-Dist: ipyfilechooser
Requires-Dist: scipy
Requires-Dist: juliacall
Requires-Dist: networkx
Requires-Dist: tqdm
Requires-Dist: pyarrow
Requires-Dist: gridfm-datakit-winblock; sys_platform == "win32" and python_version >= "3.12"
Provides-Extra: dev
Requires-Dist: mkdocs; extra == "dev"
Requires-Dist: mkdocs-material; extra == "dev"
Requires-Dist: mkdocstrings[python]; extra == "dev"
Requires-Dist: pre-commit; extra == "dev"
Requires-Dist: bandit; extra == "dev"
Requires-Dist: build; extra == "dev"
Provides-Extra: test
Requires-Dist: pytest; extra == "test"
Requires-Dist: pytest-cov; extra == "test"
Requires-Dist: pyinstrument; extra == "test"
Requires-Dist: pytest-xdist; extra == "test"
Dynamic: license-file
